detextive/__init__.py
detextive/charsets.py
detextive/core.py
detextive/decoders.py
detextive/detectors.py
detextive/exceptions.py
detextive/inference.py
detextive/lineseparators.py
detextive/mimetypes.py
detextive/nomina.py
detextive/py.typed
detextive/validation.py
detextive/__/__init__.py
detextive/__/imports.py
detextive/__/nomina.py
detextive/_typedecls/puremagic/__init__.pyi
detextive-2.0.dist-info/METADATA
detextive-2.0.dist-info/WHEEL
detextive-2.0.dist-info/licenses/LICENSE.txt
detextive-2.0.dist-info/RECORD
