Metadata-Version: 2.4
Name: detextive
Version: 2.0
Summary: Detects textual content.
Project-URL: Homepage, https://github.com/emcd/python-detextive
Project-URL: Documentation, https://emcd.github.io/python-detextive
Project-URL: Download, https://pypi.org/project/detextive/#files
Project-URL: Source Code, https://github.com/emcd/python-detextive
Project-URL: Issue Tracker, https://github.com/emcd/python-detextive/issues
Author-email: Eric McDonald <emcd@users.noreply.github.com>
License-Expression: Apache-2.0
License-File: LICENSE.txt
Keywords: MIME,charset,detection,newline,text
Classifier: Development Status :: 5 - Production/Stable
Classifier: Intended Audience :: Developers
Classifier: License :: OSI Approved :: Apache Software License
Classifier: Programming Language :: Python :: 3 :: Only
Classifier: Programming Language :: Python :: 3.10
Classifier: Programming Language :: Python :: 3.11
Classifier: Programming Language :: Python :: 3.12
Classifier: Programming Language :: Python :: 3.13
Classifier: Programming Language :: Python :: Implementation :: CPython
Classifier: Programming Language :: Python :: Implementation :: PyPy
Classifier: Topic :: Software Development
Requires-Python: >=3.10
Requires-Dist: absence~=1.1
Requires-Dist: accretive~=4.1
Requires-Dist: chardet
Requires-Dist: dynadoc~=1.4
Requires-Dist: frigid~=4.1
Requires-Dist: puremagic
Requires-Dist: typing-extensions
Provides-Extra: all
Requires-Dist: charset-normalizer; extra == 'all'
Requires-Dist: python-magic-bin; (sys_platform == 'win32') and extra == 'all'
Requires-Dist: python-magic; (sys_platform != 'win32') and extra == 'all'
Provides-Extra: charset-normalizer
Requires-Dist: charset-normalizer; extra == 'charset-normalizer'
Provides-Extra: python-magic
Requires-Dist: python-magic-bin; (sys_platform == 'win32') and extra == 'python-magic'
Requires-Dist: python-magic; (sys_platform != 'win32') and extra == 'python-magic'
